{
  "users": [
    {
      "id": 1,
      "name": "John",
      "surname": "Doe",
      "email": "john@mail.com",
      "password": "123456"
    },
    {
      "id": 2,
      "name": "Jane",
      "surname": "Doe",
      "email": "jane@mail.com",
      "password": "123456"
    },
    {
      "id": 3,
      "name": "John",
      "surname": "Smith",
      "email": "smith@mail.com",
      "password": "123456"
    },
    {
      "id": 4,
      "name": "Jane",
      "surname": "Smith",
      "email": "janesmith@mail.com",
      "password": "123456"
    },
    {
      "id": "w4cb5b93z",
      "name": "Nairobi",
      "surname": "Bodden",
      "email": "nbodden@mail.com",
      "password": "123456"
    },
    {
      "id": "9m9xpjp3i",
      "name": "Suamy",
      "surname": "Zapata",
      "email": "szapata@mail.com",
      "password": "123456"
    },
    {
      "id": "ykzttn83h",
      "name": "Jose",
      "surname": "Lainez",
      "email": "jlainez@mail.com",
      "password": "654321"
    },
    {
      "id": "vkkbtr2h8",
      "name": "Emerson",
      "surname": "Zapata",
      "email": "ezapata@gmail.com",
      "password": "1"
    },
    {
      "id": "3bzbeise2",
      "name": "Emerson",
      "surname": "Zapata",
      "email": "emerson@mail.com",
      "password": "25SuamY06"
    },
    {
      "id": "z2rkoi13k",
      "name": "bessy",
      "surname": "Rivas",
      "email": "bessy@mail.com",
      "password": "123456"
    },
    {
      "id": "hrwpjmy3p",
      "name": "David",
      "surname": "Hacelhuff",
      "email": "dhacel@mail.com",
      "password": "123456"
    }
  ]
}